[
  {
    "ScoutId": "Charlie",
    "MatchKey": "qm3",
    "Alliance": "blue",
    "DriverStation": 3,
    "TeamNumber": 4472,
    "StartingPosition": "Center",
    "ScoringSide": "Near/flush with HUB",
    "AutoNotes": "Shoot preloaded 8 balls  good accuracy but shoots rifht in front of hub and doesnt move",
    "TeleopNotes": "Shooting accuracy pretty decent seems to always have balls left in hopper so only shoots 5-10 in a cycle ",
    "ClimbSpeed": "",
    "EndgameNotes": "",
    "Disabled": false,
    "StabilityRating": "Moderately Tippy",
    "RobotStyleType": "Offensive",
    "DriverRating": "Average",
    "IntakeSpeed": "Average",
    "DefenseRating": "",
    "ShooterDefenseRating": "",
    "IntakeDefenseRating": "",
    "RatingNotes": "",
    "ThroughputSpeed": "Good",
    "TeleopClimb": null,
    "AutoClimb": false,
    "TeleopSingularCount": 0,
    "AutoSingularCount": 0,
    "AutoBatchCount": 0,
    "TeleopBatchCount": 0
  },
  {
    "ScoutId": "Charlie",
    "MatchKey": "qm2",
    "Alliance": "blue",
    "DriverStation": 3,
    "TeamNumber": 8230,
    "StartingPosition": "Depot Side",
    "ScoringSide": "",
    "AutoNotes": "No auto",
    "TeleopNotes": "Intake jammed??? Tried pushing balls back and playing defense didn\u0019t seem very effective\nDidn\u0019t shoot at all",
    "ClimbSpeed": "",
    "EndgameNotes": "",
    "Disabled": false,
    "StabilityRating": "Stable",
    "RobotStyleType": "Defensive",
    "DriverRating": "Poor",
    "IntakeSpeed": "Very Slow",
    "DefenseRating": "Poor",
    "ShooterDefenseRating": "",
    "IntakeDefenseRating": "",
    "RatingNotes": "No offense whatsoever no passing no shooting intake and shooter both not working? Defense didn\u0019t really do much tbh either",
    "ThroughputSpeed": "",
    "TeleopClimb": null,
    "AutoClimb": false,
    "TeleopSingularCount": 0,
    "AutoSingularCount": 0,
    "AutoBatchCount": 0,
    "TeleopBatchCount": 0
  },
  {
    "ScoutId": "Charlie",
    "MatchKey": "qm1",
    "Alliance": "blue",
    "DriverStation": 3,
    "TeamNumber": 122,
    "StartingPosition": "Center",
    "ScoringSide": "",
    "AutoNotes": "No auto",
    "TeleopNotes": "Shooting arc bad missed everything far way too much power\n\nTried playing defense good movement over bump very fast but didn\u0019t do anything offense wise no passing \n\nDefense pretty solid tbh so ",
    "ClimbSpeed": "",
    "EndgameNotes": "",
    "Disabled": false,
    "StabilityRating": "Stable",
    "RobotStyleType": "Defensive",
    "DriverRating": "Very Fluid",
    "IntakeSpeed": "",
    "DefenseRating": "Good",
    "ShooterDefenseRating": "",
    "IntakeDefenseRating": "",
    "RatingNotes": "No offense balls scored defense pretty ok ",
    "ThroughputSpeed": "",
    "TeleopClimb": null,
    "AutoClimb": false,
    "TeleopSingularCount": 0,
    "AutoSingularCount": 0,
    "AutoBatchCount": 0,
    "TeleopBatchCount": 0
  },
  {
    "ScoutId": "Luke",
    "MatchKey": "qm2",
    "Alliance": "red",
    "DriverStation": 2,
    "TeamNumber": 3258,
    "StartingPosition": "Center",
    "ScoringSide": "Near/flush with HUB",
    "AutoNotes": "",
    "TeleopNotes": "",
    "ClimbSpeed": "",
    "EndgameNotes": "",
    "Disabled": false,
    "StabilityRating": "Moderately Tippy",
    "RobotStyleType": "Offensive",
    "DriverRating": "Poor",
    "IntakeSpeed": "Average",
    "DefenseRating": "Okay",
    "ShooterDefenseRating": "",
    "IntakeDefenseRating": "",
    "RatingNotes": "",
    "ThroughputSpeed": "Very Good",
    "TeleopClimb": null,
    "AutoClimb": false,
    "TeleopSingularCount": 0,
    "AutoSingularCount": 0,
    "AutoBatchCount": 0,
    "TeleopBatchCount": 0
  },
  {
    "ScoutId": "nathan",
    "MatchKey": "qm1",
    "Alliance": "red",
    "DriverStation": 1,
    "TeamNumber": 2186,
    "StartingPosition": "Depot Side",
    "ScoringSide": "",
    "AutoNotes": "no auto",
    "TeleopNotes": "",
    "ClimbSpeed": "",
    "EndgameNotes": "",
    "Disabled": false,
    "StabilityRating": "Stable",
    "RobotStyleType": "Offensive",
    "DriverRating": "Average",
    "IntakeSpeed": "",
    "DefenseRating": "",
    "ShooterDefenseRating": "",
    "IntakeDefenseRating": "",
    "RatingNotes": "",
    "ThroughputSpeed": "",
    "TeleopClimb": null,
    "AutoClimb": false,
    "TeleopSingularCount": 0,
    "AutoSingularCount": 0,
    "AutoBatchCount": 0,
    "TeleopBatchCount": 0
  },
  {
    "ScoutId": "Jai",
    "MatchKey": "qm1",
    "Alliance": "blue",
    "DriverStation": 2,
    "TeamNumber": 6882,
    "StartingPosition": "Depot Side",
    "ScoringSide": "",
    "AutoNotes": "",
    "TeleopNotes": "",
    "ClimbSpeed": "",
    "EndgameNotes": "",
    "Disabled": false,
    "StabilityRating": "Stable",
    "RobotStyleType": "Offensive",
    "DriverRating": "Very Poor",
    "IntakeSpeed": "Slow",
    "DefenseRating": "",
    "ShooterDefenseRating": "Okay",
    "IntakeDefenseRating": "Okay",
    "RatingNotes": "",
    "ThroughputSpeed": "Poor",
    "TeleopClimb": null,
    "AutoClimb": false,
    "TeleopSingularCount": 0,
    "AutoSingularCount": 0,
    "AutoBatchCount": 0,
    "TeleopBatchCount": 0
  },
  {
    "ScoutId": "Jai",
    "MatchKey": "qm2",
    "Alliance": "blue",
    "DriverStation": 2,
    "TeamNumber": 8326,
    "StartingPosition": "Center",
    "ScoringSide": "",
    "AutoNotes": "",
    "TeleopNotes": "",
    "ClimbSpeed": "",
    "EndgameNotes": "",
    "Disabled": false,
    "StabilityRating": "Stable",
    "RobotStyleType": "Defensive",
    "DriverRating": "Average",
    "IntakeSpeed": "",
    "DefenseRating": "",
    "ShooterDefenseRating": "",
    "IntakeDefenseRating": "",
    "RatingNotes": "",
    "ThroughputSpeed": "",
    "TeleopClimb": null,
    "AutoClimb": false,
    "TeleopSingularCount": 0,
    "AutoSingularCount": 0,
    "AutoBatchCount": 0,
    "TeleopBatchCount": 0
  },
  {
    "ScoutId": "Jai",
    "MatchKey": "qm3",
    "Alliance": "blue",
    "DriverStation": 2,
    "TeamNumber": 116,
    "StartingPosition": "Depot Side",
    "ScoringSide": "",
    "AutoNotes": "",
    "TeleopNotes": "",
    "ClimbSpeed": "",
    "EndgameNotes": "",
    "Disabled": false,
    "StabilityRating": "Stable",
    "RobotStyleType": "Defensive",
    "DriverRating": "Very Poor",
    "IntakeSpeed": "",
    "DefenseRating": "",
    "ShooterDefenseRating": "",
    "IntakeDefenseRating": "",
    "RatingNotes": "They did not play",
    "ThroughputSpeed": "",
    "TeleopClimb": null,
    "AutoClimb": false,
    "TeleopSingularCount": 0,
    "AutoSingularCount": 0,
    "AutoBatchCount": 0,
    "TeleopBatchCount": 0
  },
  {
    "ScoutId": "Ryan Li ",
    "MatchKey": "qm2",
    "Alliance": "blue",
    "DriverStation": 1,
    "TeamNumber": 2028,
    "StartingPosition": "Center",
    "ScoringSide": "Near/flush with HUB",
    "AutoNotes": "",
    "TeleopNotes": "Missed a lot of fuel (high thru put but low accuracy)",
    "ClimbSpeed": "",
    "EndgameNotes": "",
    "Disabled": false,
    "StabilityRating": "Moderately Tippy",
    "RobotStyleType": "Offensive",
    "DriverRating": "Fluid",
    "IntakeSpeed": "Average",
    "DefenseRating": "",
    "ShooterDefenseRating": "",
    "IntakeDefenseRating": "",
    "RatingNotes": "",
    "ThroughputSpeed": "Very Good",
    "TeleopClimb": null,
    "AutoClimb": false,
    "TeleopSingularCount": 0,
    "AutoSingularCount": 0,
    "AutoBatchCount": 0,
    "TeleopBatchCount": 0
  },
  {
    "ScoutId": "Ryan Li ",
    "MatchKey": "qm3",
    "Alliance": "blue",
    "DriverStation": 1,
    "TeamNumber": 526,
    "StartingPosition": "Human-Player Side",
    "ScoringSide": "",
    "AutoNotes": "",
    "TeleopNotes": "Intake broke did a lot of pushing balls",
    "ClimbSpeed": "",
    "EndgameNotes": "",
    "Disabled": false,
    "StabilityRating": "Moderately Tippy",
    "RobotStyleType": "Offensive",
    "DriverRating": "Average",
    "IntakeSpeed": "",
    "DefenseRating": "",
    "ShooterDefenseRating": "",
    "IntakeDefenseRating": "",
    "RatingNotes": "Hopper popped out as well ",
    "ThroughputSpeed": "Okay",
    "TeleopClimb": null,
    "AutoClimb": false,
    "TeleopSingularCount": 0,
    "AutoSingularCount": 0,
    "AutoBatchCount": 0,
    "TeleopBatchCount": 0
  },
  {
    "ScoutId": "Luke",
    "MatchKey": "4",
    "Alliance": "red",
    "DriverStation": 2,
    "TeamNumber": 2890,
    "StartingPosition": "Center",
    "ScoringSide": "",
    "AutoNotes": "Became disabled not moving but light blinking",
    "TeleopNotes": "",
    "ClimbSpeed": "",
    "EndgameNotes": "",
    "Disabled": true,
    "StabilityRating": "Stable",
    "RobotStyleType": "Offensive",
    "DriverRating": "Average",
    "IntakeSpeed": "",
    "DefenseRating": "",
    "ShooterDefenseRating": "",
    "IntakeDefenseRating": "",
    "RatingNotes": "Disabled quickly before driving stule could be evaluated",
    "ThroughputSpeed": "",
    "TeleopClimb": null,
    "AutoClimb": false,
    "TeleopSingularCount": 0,
    "AutoSingularCount": 0,
    "AutoBatchCount": 0,
    "TeleopBatchCount": 0
  },
  {
    "ScoutId": "Charlie",
    "MatchKey": "qm4",
    "Alliance": "blue",
    "DriverStation": 3,
    "TeamNumber": 2363,
    "StartingPosition": "Depot Side",
    "ScoringSide": "Human Player Side",
    "AutoNotes": "Scored gathered some balls shot some more",
    "TeleopNotes": "Shot a few balls and then stopped moving for ENTIRE teleop",
    "ClimbSpeed": "",
    "EndgameNotes": "",
    "Disabled": false,
    "StabilityRating": "Moderately Tippy",
    "RobotStyleType": "Offensive",
    "DriverRating": "Average",
    "IntakeSpeed": "",
    "DefenseRating": "",
    "ShooterDefenseRating": "",
    "IntakeDefenseRating": "",
    "RatingNotes": "Basically stopped moving the entire time&not sure why they didn\u0019t disable ",
    "ThroughputSpeed": "",
    "TeleopClimb": null,
    "AutoClimb": false,
    "TeleopSingularCount": 0,
    "AutoSingularCount": 0,
    "AutoBatchCount": 0,
    "TeleopBatchCount": 0
  },
  {
    "ScoutId": "Amaan",
    "MatchKey": "qm4",
    "Alliance": "red",
    "DriverStation": 1,
    "TeamNumber": 1895,
    "StartingPosition": "Depot Side",
    "ScoringSide": "",
    "AutoNotes": "Passed and lowk sat around ",
    "TeleopNotes": "nothing again&",
    "ClimbSpeed": "",
    "EndgameNotes": "na",
    "Disabled": false,
    "StabilityRating": "Stable",
    "RobotStyleType": "Defensive",
    "DriverRating": "Average",
    "IntakeSpeed": "Slow",
    "DefenseRating": "Poor",
    "ShooterDefenseRating": "Okay",
    "IntakeDefenseRating": "Poor",
    "RatingNotes": "mid ",
    "ThroughputSpeed": "Poor",
    "TeleopClimb": null,
    "AutoClimb": false,
    "TeleopSingularCount": 0,
    "AutoSingularCount": 0,
    "AutoBatchCount": 0,
    "TeleopBatchCount": 0
  },
  {
    "ScoutId": "arnav",
    "MatchKey": "qm4",
    "Alliance": "red",
    "DriverStation": 3,
    "TeamNumber": 3136,
    "StartingPosition": "Depot Side",
    "ScoringSide": "Depot Side",
    "AutoNotes": "",
    "TeleopNotes": "",
    "ClimbSpeed": "",
    "EndgameNotes": "",
    "Disabled": false,
    "StabilityRating": "Stable",
    "RobotStyleType": "Offensive",
    "DriverRating": "Very Fluid",
    "IntakeSpeed": "Fast",
    "DefenseRating": "",
    "ShooterDefenseRating": "",
    "IntakeDefenseRating": "",
    "RatingNotes": "",
    "ThroughputSpeed": "Very Good",
    "TeleopClimb": null,
    "AutoClimb": false,
    "TeleopSingularCount": 0,
    "AutoSingularCount": 0,
    "AutoBatchCount": 0,
    "TeleopBatchCount": 0
  },
  {
    "ScoutId": "amaan",
    "MatchKey": "qm5",
    "Alliance": "red",
    "DriverStation": 1,
    "TeamNumber": 9072,
    "StartingPosition": "Depot Side",
    "ScoringSide": "Depot Side",
    "AutoNotes": "",
    "TeleopNotes": ">y>y>y>y>y",
    "ClimbSpeed": "",
    "EndgameNotes": "",
    "Disabled": false,
    "StabilityRating": "Stable",
    "RobotStyleType": "Offensive",
    "DriverRating": "Very Fluid",
    "IntakeSpeed": "Fast",
    "DefenseRating": "Very Good",
    "ShooterDefenseRating": "Very Good",
    "IntakeDefenseRating": "Very Good",
    "RatingNotes": "amazing before intake broke",
    "ThroughputSpeed": "Very Good",
    "TeleopClimb": null,
    "AutoClimb": false,
    "TeleopSingularCount": 0,
    "AutoSingularCount": 0,
    "AutoBatchCount": 0,
    "TeleopBatchCount": 0
  },
  {
    "ScoutId": "arnav",
    "MatchKey": "qm5",
    "Alliance": "red",
    "DriverStation": 3,
    "TeamNumber": 4638,
    "StartingPosition": "Center",
    "ScoringSide": "Near/flush with HUB",
    "AutoNotes": "",
    "TeleopNotes": "",
    "ClimbSpeed": "",
    "EndgameNotes": "",
    "Disabled": false,
    "StabilityRating": "Stable",
    "RobotStyleType": "Defensive",
    "DriverRating": "Fluid",
    "IntakeSpeed": "Average",
    "DefenseRating": "Poor",
    "ShooterDefenseRating": "",
    "IntakeDefenseRating": "",
    "RatingNotes": "",
    "ThroughputSpeed": "Okay",
    "TeleopClimb": null,
    "AutoClimb": false,
    "TeleopSingularCount": 0,
    "AutoSingularCount": 0,
    "AutoBatchCount": 0,
    "TeleopBatchCount": 0
  },
  {
    "ScoutId": "Luke",
    "MatchKey": "5",
    "Alliance": "red",
    "DriverStation": 2,
    "TeamNumber": 5338,
    "StartingPosition": "Human-Player Side",
    "ScoringSide": "Human Player Side",
    "AutoNotes": "",
    "TeleopNotes": "",
    "ClimbSpeed": "",
    "EndgameNotes": "",
    "Disabled": false,
    "StabilityRating": "Stable",
    "RobotStyleType": "Offensive",
    "DriverRating": "Fluid",
    "IntakeSpeed": "Average",
    "DefenseRating": "",
    "ShooterDefenseRating": "",
    "IntakeDefenseRating": "",
    "RatingNotes": "",
    "ThroughputSpeed": "Okay",
    "TeleopClimb": null,
    "AutoClimb": false,
    "TeleopSingularCount": 0,
    "AutoSingularCount": 0,
    "AutoBatchCount": 0,
    "TeleopBatchCount": 0
  },
  {
    "ScoutId": "Jai",
    "MatchKey": "qm4",
    "Alliance": "blue",
    "DriverStation": 2,
    "TeamNumber": 5587,
    "StartingPosition": "Depot Side",
    "ScoringSide": "",
    "AutoNotes": "",
    "TeleopNotes": "",
    "ClimbSpeed": "",
    "EndgameNotes": "",
    "Disabled": false,
    "StabilityRating": "Very Tippy",
    "RobotStyleType": "Offensive",
    "DriverRating": "Poor",
    "IntakeSpeed": "Very Slow",
    "DefenseRating": "Poor",
    "ShooterDefenseRating": "",
    "IntakeDefenseRating": "",
    "RatingNotes": "",
    "ThroughputSpeed": "",
    "TeleopClimb": null,
    "AutoClimb": false,
    "TeleopSingularCount": 0,
    "AutoSingularCount": 0,
    "AutoBatchCount": 0,
    "TeleopBatchCount": 0
  },
  {
    "ScoutId": "Jai",
    "MatchKey": "qm5",
    "Alliance": "blue",
    "DriverStation": 2,
    "TeamNumber": 1908,
    "StartingPosition": "Human-Player Side",
    "ScoringSide": "",
    "AutoNotes": "",
    "TeleopNotes": "",
    "ClimbSpeed": "",
    "EndgameNotes": "",
    "Disabled": false,
    "StabilityRating": "Stable",
    "RobotStyleType": "Offensive",
    "DriverRating": "Very Fluid",
    "IntakeSpeed": "Fast",
    "DefenseRating": "",
    "ShooterDefenseRating": "Good",
    "IntakeDefenseRating": "",
    "RatingNotes": "really really good carried their alliance made 90% of shots",
    "ThroughputSpeed": "Good",
    "TeleopClimb": null,
    "AutoClimb": false,
    "TeleopSingularCount": 0,
    "AutoSingularCount": 0,
    "AutoBatchCount": 0,
    "TeleopBatchCount": 0
  },
  {
    "ScoutId": "Ryan Li ",
    "MatchKey": "qm4",
    "Alliance": "blue",
    "DriverStation": 1,
    "TeamNumber": 612,
    "StartingPosition": "Center",
    "ScoringSide": "",
    "AutoNotes": "",
    "TeleopNotes": "Beached",
    "ClimbSpeed": "",
    "EndgameNotes": "",
    "Disabled": false,
    "StabilityRating": "Stable",
    "RobotStyleType": "Offensive",
    "DriverRating": "Average",
    "IntakeSpeed": "Average",
    "DefenseRating": "",
    "ShooterDefenseRating": "",
    "IntakeDefenseRating": "",
    "RatingNotes": "Got beached for half the game ",
    "ThroughputSpeed": "Good",
    "TeleopClimb": null,
    "AutoClimb": false,
    "TeleopSingularCount": 0,
    "AutoSingularCount": 0,
    "AutoBatchCount": 0,
    "TeleopBatchCount": 0
  },
  {
    "ScoutId": "Ryan Li ",
    "MatchKey": "qm5",
    "Alliance": "blue",
    "DriverStation": 1,
    "TeamNumber": 5549,
    "StartingPosition": "Depot Side",
    "ScoringSide": "",
    "AutoNotes": "",
    "TeleopNotes": "Beached",
    "ClimbSpeed": "",
    "EndgameNotes": "",
    "Disabled": false,
    "StabilityRating": "Moderately Tippy",
    "RobotStyleType": "Offensive",
    "DriverRating": "Average",
    "IntakeSpeed": "Fast",
    "DefenseRating": "",
    "ShooterDefenseRating": "",
    "IntakeDefenseRating": "",
    "RatingNotes": "Gets stuck under trench",
    "ThroughputSpeed": "Good",
    "TeleopClimb": null,
    "AutoClimb": false,
    "TeleopSingularCount": 0,
    "AutoSingularCount": 0,
    "AutoBatchCount": 0,
    "TeleopBatchCount": 0
  },
  {
    "ScoutId": "Charlie",
    "MatchKey": "qm5",
    "Alliance": "blue",
    "DriverStation": 3,
    "TeamNumber": 5353,
    "StartingPosition": "Center",
    "ScoringSide": "Near/flush with HUB",
    "AutoNotes": "All shots missed straight into hub",
    "TeleopNotes": "Shooting not good miss almost everything big hopper helped a little bit with funneling balls into alliance zone",
    "ClimbSpeed": "",
    "EndgameNotes": "",
    "Disabled": false,
    "StabilityRating": "Stable",
    "RobotStyleType": "Defensive",
    "DriverRating": "Average",
    "IntakeSpeed": "Slow",
    "DefenseRating": "",
    "ShooterDefenseRating": "",
    "IntakeDefenseRating": "",
    "RatingNotes": "Lowk didn\u0019t do that much",
    "ThroughputSpeed": "Very Poor",
    "TeleopClimb": null,
    "AutoClimb": false,
    "TeleopSingularCount": 0,
    "AutoSingularCount": 0,
    "AutoBatchCount": 0,
    "TeleopBatchCount": 0
  }
]